scaler/CMakeLists.txt
scaler/__init__.py
scaler/about.py
scaler/client/__init__.py
scaler/client/client.py
scaler/client/future.py
scaler/client/object_buffer.py
scaler/client/object_reference.py
scaler/client/agent/__init__.py
scaler/client/agent/client_agent.py
scaler/client/agent/disconnect_manager.py
scaler/client/agent/future_manager.py
scaler/client/agent/heartbeat_manager.py
scaler/client/agent/mixins.py
scaler/client/agent/object_manager.py
scaler/client/agent/task_manager.py
scaler/client/serializer/__init__.py
scaler/client/serializer/default.py
scaler/client/serializer/mixins.py
scaler/cluster/__init__.py
scaler/cluster/cluster.py
scaler/cluster/combo.py
scaler/cluster/scheduler.py
scaler/entry_points/__init__.py
scaler/entry_points/cluster.py
scaler/entry_points/object_storage_server.py
scaler/entry_points/scheduler.py
scaler/entry_points/symphony_cluster.py
scaler/entry_points/top.py
scaler/entry_points/webui.py
scaler/io/__init__.py
scaler/io/async_binder.py
scaler/io/async_connector.py
scaler/io/config.py
scaler/io/sync_connector.py
scaler/io/sync_subscriber.py
scaler/io/utility.py
scaler/io/ymq/CMakeLists.txt
scaler/io/ymq/bytes.hpp
scaler/io/ymq/common.hpp
scaler/io/ymq/configuration.hpp
scaler/io/ymq/coro_awaitable.h
scaler/io/ymq/coro_context.cpp
scaler/io/ymq/coro_context.h
scaler/io/ymq/coro_task.h
scaler/io/ymq/defs.h
scaler/io/ymq/epoll_context.hpp
scaler/io/ymq/event_loop.hpp
scaler/io/ymq/event_loop_backend.hpp
scaler/io/ymq/event_loop_thread.hpp
scaler/io/ymq/event_manager.hpp
scaler/io/ymq/file_descriptor.hpp
scaler/io/ymq/interruptive_concurrent_queue.hpp
scaler/io/ymq/io_socket.hpp
scaler/io/ymq/main.hpp
scaler/io/ymq/message_connection.hpp
scaler/io/ymq/message_connection_tcp.hpp
scaler/io/ymq/readme.md
scaler/io/ymq/tcp_client.hpp
scaler/io/ymq/tcp_server.hpp
scaler/io/ymq/timed_concurrent_queue.hpp
scaler/io/ymq/third_party/concurrentqueue.h
scaler/lib/libserver.so
scaler-1.9.9.dist-info/METADATA
scaler-1.9.9.dist-info/WHEEL
scaler-1.9.9.dist-info/entry_points.txt
scaler-1.9.9.dist-info/RECORD
scaler-1.9.9.dist-info/licenses/LICENSE
