Metadata-Version: 2.2
Name: scaler
Version: 1.9.9
Summary: Scaler Distribution Framework
Author-Email: Citi <opensource@citi.com>
License: Apache 2.0
Classifier: Programming Language :: Python :: 3
Classifier: License :: OSI Approved :: Apache Software License
Classifier: Intended Audience :: Developers
Classifier: Operating System :: OS Independent
Classifier: Topic :: System :: Distributed Computing
Project-URL: Home, https://github.com/Citi/scaler
Requires-Python: >=3.10
Requires-Dist: bidict
Requires-Dist: cloudpickle
Requires-Dist: graphlib-backport; python_version < "3.9"
Requires-Dist: psutil==7.0.0
Requires-Dist: pycapnp==2.0.0
Requires-Dist: pyzmq
Requires-Dist: tblib
Provides-Extra: uvloop
Requires-Dist: uvloop; extra == "uvloop"
Provides-Extra: graphblas
Requires-Dist: python-graphblas; extra == "graphblas"
Requires-Dist: numpy==2.2.5; extra == "graphblas"
Provides-Extra: gui
Requires-Dist: nicegui[plotly]==2.14.1; extra == "gui"
Provides-Extra: all
Requires-Dist: python-graphblas; extra == "all"
Requires-Dist: numpy==2.2.5; extra == "all"
Requires-Dist: uvloop; extra == "all"
Requires-Dist: nicegui[plotly]==2.14.1; extra == "all"
